esm_full_backup/__init__.py
esm_full_backup/console.py
esm_full_backup/esm_full_backup.py
esm_full_backup-0.0.1.dist-info/DESCRIPTION.rst
esm_full_backup-0.0.1.dist-info/METADATA
esm_full_backup-0.0.1.dist-info/RECORD
esm_full_backup-0.0.1.dist-info/WHEEL
esm_full_backup-0.0.1.dist-info/entry_points.txt
esm_full_backup-0.0.1.dist-info/metadata.json
esm_full_backup-0.0.1.dist-info/top_level.txt
