Metadata-Version: 2.0
Name: esm-full-backup
Version: 0.0.1
Summary: Kicks off full backup for McAfee ESM
Home-page: https://github.com/andywalden/esm_full_backup
Author: Andy Walden
Author-email: aw@krakencodes.com
License: ISC
Keywords: esm_full_backup
Platform: UNKNOWN
Classifier: Development Status :: 4 - Beta
Classifier: Intended Audience :: Developers
Classifier: License :: OSI Approved :: ISC License (ISCL)
Classifier: Natural Language :: English
Classifier: Operating System :: MacOS
Classifier: Operating System :: Unix
Classifier: Operating System :: Microsoft :: Windows
Classifier: Programming Language :: Python :: 3.4
Classifier: Programming Language :: Python :: 3.5
Classifier: Programming Language :: Python :: 3.6
Classifier: Programming Language :: Python :: 3 :: Only
Requires-Python: >=3
Requires-Dist: requests
